stepRNA/__init__.py
stepRNA/commands.py
stepRNA/general.py
stepRNA/index_bowtie.py
stepRNA/make_unique.py
stepRNA/miRNAfilter.py
stepRNA/output.py
stepRNA/processing.py
stepRNA/remove_exact.py
stepRNA/stepRNA_cigar_process.py
stepRNA/stepRNA_output.py
stepRNA/stepRNA_run_bowtie.py
stepRNA-1.0.6.data/scripts/stepRNA
stepRNA-1.0.6.data/scripts/stepRNA_cigar_process.py
stepRNA-1.0.6.data/scripts/stepRNA_run_bowtie.py
stepRNA-1.0.6.dist-info/LICENSE
stepRNA-1.0.6.dist-info/METADATA
stepRNA-1.0.6.dist-info/WHEEL
stepRNA-1.0.6.dist-info/top_level.txt
stepRNA-1.0.6.dist-info/RECORD
