Metadata-Version: 2.1
Name: stepRNA
Version: 1.0.6
Summary: Align short RNA seqeuncing reads to determine the length of of overhang.
Home-page: https://github.com/bmm514/stepRNA.git
Author: Ben Murcott
Author-email: bmm41@bath.ac.uk
License: MIT
Keywords: Dicer,RNA,genomics,processing,sRNA,miRNA
Classifier: Programming Language :: Python :: 3
Classifier: License :: OSI Approved :: MIT License
Classifier: Operating System :: Unix
Requires-Python: >=3.6
License-File: LICENSE
Requires-Dist: pysam (>=0.16.0.1)
Requires-Dist: biopython (>=1.78)
Requires-Dist: numpy (>=1.19.0)
Requires-Dist: tqdm (>=4.62.3)
Requires-Dist: alive-progress (>=3.0.1)
